dparse/__init__.py
dparse/dependencies.py
dparse/errors.py
dparse/filetypes.py
dparse/parser.py
dparse/regex.py
dparse/updater.py
dparse-0.6.3.dist-info/LICENSE
dparse-0.6.3.dist-info/METADATA
dparse-0.6.3.dist-info/WHEEL
dparse-0.6.3.dist-info/top_level.txt
dparse-0.6.3.dist-info/RECORD
