Metadata-Version: 2.1
Name: dparse
Version: 0.6.3
Summary: A parser for Python dependency files
Home-page: https://github.com/pyupio/dparse
Author: Jannis Gebauer
Author-email: support@pyup.io
License: MIT license
Keywords: dparse
Classifier: Development Status :: 5 - Production/Stable
Classifier: Intended Audience :: Developers
Classifier: License :: OSI Approved :: MIT License
Classifier: Natural Language :: English
Classifier: Programming Language :: Python :: 3
Classifier: Programming Language :: Python :: 3.6
Classifier: Programming Language :: Python :: 3.7
Classifier: Programming Language :: Python :: 3.8
Classifier: Programming Language :: Python :: 3.9
Classifier: Programming Language :: Python :: 3.10
Requires-Python: >=3.6
Provides-Extra: pipenv
Provides-Extra: conda
License-File: LICENSE
